LICENSE
MANIFEST.in
README.md
setup.py
aws_python_utils/__init__.py
aws_python_utils/__version__.py
aws_python_utils/ec2.py
aws_python_utils/s3.py
aws_python_utils/secretmanager.py
aws_python_utils.egg-info/PKG-INFO
aws_python_utils.egg-info/SOURCES.txt
aws_python_utils.egg-info/dependency_links.txt
aws_python_utils.egg-info/requires.txt
aws_python_utils.egg-info/top_level.txt