Metadata-Version: 2.1
Name: aws-python-utils
Version: 0.0.7
Summary: Simplify use of AWS resources in your code with aws-python-utils
Home-page: https://github.com/silvermullet/aws-python-utils
Author: Zane Williamson
Author-email: zane.williamson@gmail.com
License: MIT
Platform: UNKNOWN
Classifier: License :: OSI Approved :: MIT License
Classifier: Programming Language :: Python
Classifier: Programming Language :: Python :: 3
Classifier: Programming Language :: Python :: 3.6
Classifier: Programming Language :: Python :: Implementation :: CPython
Classifier: Programming Language :: Python :: Implementation :: PyPy
Requires-Python: >=3.6.0
